collective.purgebyid-1.2.2-py3.12-nspkg.pth
collective/purgebyid/__init__.py
collective/purgebyid/adapter.py
collective/purgebyid/api.py
collective/purgebyid/browser.py
collective/purgebyid/configure.zcml
collective/purgebyid/events.py
collective/purgebyid/interfaces.py
collective/purgebyid/purge.py
collective/purgebyid/testing.py
collective/purgebyid/tests/__init__.py
collective/purgebyid/tests/document_with_dependencies.pt
collective/purgebyid/tests/test_purge.py
collective.purgebyid-1.2.2.dist-info/LICENSE.GPL
collective.purgebyid-1.2.2.dist-info/LICENSE.txt
collective.purgebyid-1.2.2.dist-info/METADATA
collective.purgebyid-1.2.2.dist-info/WHEEL
collective.purgebyid-1.2.2.dist-info/entry_points.txt
collective.purgebyid-1.2.2.dist-info/namespace_packages.txt
collective.purgebyid-1.2.2.dist-info/top_level.txt
collective.purgebyid-1.2.2.dist-info/RECORD
