Metadata-Version: 2.1
Name: collective.purgebyid
Version: 1.2.2
Summary: p.a.caching add-on for a better purging policy
Home-page: https://github.com/collective/collective.purgebyid
Author: Mauro Amico
Author-email: mauro.amico@gmail.com
License: gpl
Keywords: plone caching
Classifier: Environment :: Web Environment
Classifier: Framework :: Plone
Classifier: Framework :: Plone :: Addon
Classifier: Operating System :: OS Independent
Classifier: Programming Language :: Python
Classifier: Programming Language :: Python :: 2.7
Classifier: Programming Language :: Python :: 3.7
Classifier: Programming Language :: Python :: 3.8
Classifier: Programming Language :: Python :: 3.9
Classifier: Programming Language :: Python :: 3.10
Classifier: Programming Language :: Python :: 3.11
Classifier: Programming Language :: Python :: 3.12
Classifier: Development Status :: 5 - Production/Stable
Classifier: Topic :: Software Development :: Libraries :: Python Modules
License-File: LICENSE.GPL
License-File: LICENSE.txt
Requires-Dist: setuptools
Requires-Dist: six
Requires-Dist: plone.uuid
Provides-Extra: test
Requires-Dist: plone.app.testing ; extra == 'test'
Requires-Dist: plone.api ; extra == 'test'
Requires-Dist: plone.app.contenttypes ; extra == 'test'
